<transactionForm scriptid="custform_oro_21000_bill_payment" standard="STANDARDBILLPAYMENT">
  <name>*⛵ Bill Payment</name>
  <recordType>VENDORPAYMENT</recordType>
  <inactive>F</inactive>
  <preferred>T</preferred>
  <mainFields>
    <fieldGroup scriptid="primaryinformation">
      <label>Primary Information</label>
      <visible>T</visible>
      <showTitle>T</showTitle>
      <singleColumn>F</singleColumn>
      <fields position="MIDDLE">
        <field>
          <id>TRANSACTIONNUMBER</id>
          <label>Transaction Number</label>
          <visible>T</visible>
          <mandatory>F</mandatory>
          <displayType>NORMAL</displayType>
          <columnBreak>F</columnBreak>
          <sameRowAsPrevious>F</sameRowAsPrevious>
        </field>
        <field>
          <id>ENTITY</id>
          <label>Payee</label>
          <visible>T</visible>
          <mandatory>T</mandatory>
          <displayType>NORMAL</displayType>
          <columnBreak>F</columnBreak>
          <sameRowAsPrevious>F</sameRowAsPrevious>
        </field>
        <field>
          <id>SUBSIDIARY</id>
          <label>Subsidiary</label>
          <visible>T</visible>
          <mandatory>T</mandatory>
          <displayType>NORMAL</displayType>
          <columnBreak>F</columnBreak>
          <sameRowAsPrevious>F</sameRowAsPrevious>
        </field>
        <field>
          <id>APACCT</id>
          <label>A/P Account</label>
          <visible>T</visible>
          <mandatory>F</mandatory>
          <displayType>NORMAL</displayType>
          <columnBreak>F</columnBreak>
          <sameRowAsPrevious>F</sameRowAsPrevious>
        </field>
        <field>
          <id>BALANCE</id>
          <label>Balance</label>
          <visible>T</visible>
          <mandatory>F</mandatory>
          <displayType>INLINETEXT</displayType>
          <columnBreak>F</columnBreak>
          <sameRowAsPrevious>F</sameRowAsPrevious>
        </field>
        <field>
          <id>AVAILABLEBALANCE</id>
          <label>Available Balance</label>
          <visible>T</visible>
          <mandatory>F</mandatory>
          <displayType>NORMAL</displayType>
          <columnBreak>F</columnBreak>
          <sameRowAsPrevious>F</sameRowAsPrevious>
        </field>
        <field>
          <id>TOTAL</id>
          <label>Amount</label>
          <visible>T</visible>
          <mandatory>T</mandatory>
          <displayType>NORMAL</displayType>
          <columnBreak>F</columnBreak>
          <sameRowAsPrevious>F</sameRowAsPrevious>
        </field>
        <field>
          <id>ACCOUNT</id>
          <label>Bank Account</label>
          <visible>T</visible>
          <mandatory>T</mandatory>
          <displayType>NORMAL</displayType>
          <columnBreak>T</columnBreak>
          <sameRowAsPrevious>F</sameRowAsPrevious>
        </field>
        <field>
          <id>DEPARTMENT</id>
          <label>Department</label>
          <visible>T</visible>
          <mandatory>F</mandatory>
          <displayType>NORMAL</displayType>
          <columnBreak>F</columnBreak>
          <sameRowAsPrevious>F</sameRowAsPrevious>
        </field>
        <field>
          <id>CURRENCY</id>
          <label>Currency</label>
          <visible>T</visible>
          <mandatory>T</mandatory>
          <displayType>NORMAL</displayType>
          <columnBreak>F</columnBreak>
          <sameRowAsPrevious>F</sameRowAsPrevious>
        </field>
        <field>
          <id>EXCHANGERATE</id>
          <label>Exchange Rate</label>
          <visible>T</visible>
          <mandatory>T</mandatory>
          <displayType>NORMAL</displayType>
          <columnBreak>F</columnBreak>
          <sameRowAsPrevious>T</sameRowAsPrevious>
        </field>
        <field>
          <id>TRANDATE</id>
          <label>Date</label>
          <visible>T</visible>
          <mandatory>T</mandatory>
          <displayType>NORMAL</displayType>
          <columnBreak>F</columnBreak>
          <sameRowAsPrevious>F</sameRowAsPrevious>
        </field>
        <field>
          <id>POSTINGPERIOD</id>
          <label>Posting Period</label>
          <visible>T</visible>
          <mandatory>F</mandatory>
          <displayType>NORMAL</displayType>
          <columnBreak>F</columnBreak>
          <sameRowAsPrevious>T</sameRowAsPrevious>
        </field>
        <field>
          <id>VOIDJOURNAL</id>
          <label>Voided On</label>
          <visible>T</visible>
          <mandatory>F</mandatory>
          <displayType>NORMAL</displayType>
          <columnBreak>F</columnBreak>
          <sameRowAsPrevious>F</sameRowAsPrevious>
        </field>
        <field>
          <id>TOBEPRINTED</id>
          <label>To Be Printed</label>
          <visible>T</visible>
          <mandatory>F</mandatory>
          <displayType>NORMAL</displayType>
          <columnBreak>T</columnBreak>
          <sameRowAsPrevious>F</sameRowAsPrevious>
          <checkBoxDefault>USE_FIELD_DEFAULT</checkBoxDefault>
        </field>
        <field>
          <id>PRINTVOUCHER</id>
          <label>Voucher</label>
          <visible>T</visible>
          <mandatory>F</mandatory>
          <displayType>NORMAL</displayType>
          <columnBreak>F</columnBreak>
          <sameRowAsPrevious>T</sameRowAsPrevious>
          <checkBoxDefault>USE_FIELD_DEFAULT</checkBoxDefault>
        </field>
        <field>
          <id>TRANID</id>
          <label>Cheque #</label>
          <visible>T</visible>
          <mandatory>F</mandatory>
          <displayType>NORMAL</displayType>
          <columnBreak>F</columnBreak>
          <sameRowAsPrevious>F</sameRowAsPrevious>
        </field>
        <field>
          <id>NEXTAPPROVER</id>
          <label>Next Approver</label>
          <visible>T</visible>
          <mandatory>F</mandatory>
          <displayType>NORMAL</displayType>
          <columnBreak>T</columnBreak>
          <sameRowAsPrevious>F</sameRowAsPrevious>
        </field>
        <field>
          <id>APPROVALSTATUS</id>
          <label>Approval Status</label>
          <visible>T</visible>
          <mandatory>F</mandatory>
          <displayType>NORMAL</displayType>
          <columnBreak>F</columnBreak>
          <sameRowAsPrevious>F</sameRowAsPrevious>
        </field>
        <field>
          <id>MEMO</id>
          <label>Memo</label>
          <visible>T</visible>
          <mandatory>F</mandatory>
          <displayType>NORMAL</displayType>
          <columnBreak>F</columnBreak>
          <sameRowAsPrevious>F</sameRowAsPrevious>
        </field>
        <field>
          <id>ISINTRANSITPAYMENT</id>
          <label>In-Transit</label>
          <visible>T</visible>
          <mandatory>F</mandatory>
          <displayType>NORMAL</displayType>
          <columnBreak>F</columnBreak>
          <sameRowAsPrevious>F</sameRowAsPrevious>
        </field>
      </fields>
    </fieldGroup>
    <fieldGroup scriptid="classification">
      <label>Classification</label>
      <visible>T</visible>
      <showTitle>T</showTitle>
      <singleColumn>F</singleColumn>
    </fieldGroup>
    <fieldGroup scriptid="intercompanymanagement">
      <label>Intercompany Management</label>
      <visible>T</visible>
      <showTitle>T</showTitle>
      <singleColumn>F</singleColumn>
    </fieldGroup>
    <defaultFieldGroup>
      <fields position="MIDDLE">
        <field>
          <id>EXCLUDEFROMGLNUMBERING</id>
          <label>Exclude from GL Audit Numbering</label>
          <visible>F</visible>
          <mandatory>F</mandatory>
          <displayType>NORMAL</displayType>
          <columnBreak>F</columnBreak>
          <sameRowAsPrevious>F</sameRowAsPrevious>
        </field>
        <field>
          <id>GENERATETRANIDONSAVE</id>
          <label>Generate Document Number on Save</label>
          <visible>F</visible>
          <mandatory>F</mandatory>
          <displayType>NORMAL</displayType>
          <columnBreak>F</columnBreak>
          <sameRowAsPrevious>F</sameRowAsPrevious>
          <checkBoxDefault>UNCHECKED</checkBoxDefault>
        </field>
        <field>
          <id>[type=transactionbodycustomfield, scriptid=cseg_oro_faproject]</id>
          <label>FA Project</label>
          <visible>F</visible>
          <mandatory>F</mandatory>
          <displayType>NORMAL</displayType>
          <columnBreak>F</columnBreak>
          <sameRowAsPrevious>F</sameRowAsPrevious>
        </field>
        <field>
          <id>[type=transactionbodycustomfield, scriptid=cseg_oro_facategory]</id>
          <label>FA Category</label>
          <visible>F</visible>
          <mandatory>F</mandatory>
          <displayType>NORMAL</displayType>
          <columnBreak>F</columnBreak>
          <sameRowAsPrevious>F</sameRowAsPrevious>
        </field>
        <field>
          <id>LOCATION</id>
          <label>Location</label>
          <visible>F</visible>
          <mandatory>F</mandatory>
          <displayType>NORMAL</displayType>
          <columnBreak>F</columnBreak>
          <sameRowAsPrevious>F</sameRowAsPrevious>
        </field>
        <field>
          <id>[scriptid=custbody_11724_pay_bank_fees]</id>
          <label>Vendor Bank Fees</label>
          <visible>F</visible>
          <mandatory>F</mandatory>
          <displayType>DISABLED</displayType>
          <columnBreak>F</columnBreak>
          <sameRowAsPrevious>F</sameRowAsPrevious>
          <checkBoxDefault>USE_FIELD_DEFAULT</checkBoxDefault>
        </field>
        <field>
          <id>[scriptid=custbody_document_date]</id>
          <label>Document Date</label>
          <visible>F</visible>
          <mandatory>F</mandatory>
          <displayType>NORMAL</displayType>
          <columnBreak>F</columnBreak>
          <sameRowAsPrevious>F</sameRowAsPrevious>
        </field>
        <field>
          <id>[scriptid=custbody_2663_reference_num]</id>
          <label>ACH/EFT Reference No.</label>
          <visible>F</visible>
          <mandatory>F</mandatory>
          <displayType>NORMAL</displayType>
          <columnBreak>F</columnBreak>
          <sameRowAsPrevious>F</sameRowAsPrevious>
        </field>
        <field>
          <id>[scriptid=custbody_oro_3010_esr_no]</id>
          <label>ESR Number</label>
          <visible>F</visible>
          <mandatory>F</mandatory>
          <displayType>NORMAL</displayType>
          <columnBreak>F</columnBreak>
          <sameRowAsPrevious>F</sameRowAsPrevious>
        </field>
        <field>
          <id>[scriptid=custbody_ste_transaction_type]</id>
          <label>Tax Transaction Type</label>
          <visible>F</visible>
          <mandatory>F</mandatory>
          <displayType>NORMAL</displayType>
          <columnBreak>F</columnBreak>
          <sameRowAsPrevious>F</sameRowAsPrevious>
        </field>
        <field>
          <id>[scriptid=custbody_fam_jrn_reversal_date]</id>
          <label>Reversal Date</label>
          <visible>F</visible>
          <mandatory>F</mandatory>
          <displayType>NORMAL</displayType>
          <columnBreak>F</columnBreak>
          <sameRowAsPrevious>F</sameRowAsPrevious>
        </field>
        <field>
          <id>[scriptid=custbody_fam_jrn_reversal_no]</id>
          <label>Reversal Number</label>
          <visible>F</visible>
          <mandatory>F</mandatory>
          <displayType>INLINETEXT</displayType>
          <columnBreak>F</columnBreak>
          <sameRowAsPrevious>F</sameRowAsPrevious>
        </field>
        <field>
          <id>[scriptid=custbody_fam_lp_company]</id>
          <label>Lease Company</label>
          <visible>F</visible>
          <mandatory>T</mandatory>
          <displayType>NORMAL</displayType>
          <columnBreak>F</columnBreak>
          <sameRowAsPrevious>F</sameRowAsPrevious>
        </field>
        <field>
          <id>[scriptid=custbody_fam_lp_contractnum]</id>
          <label>Lease Contract Number</label>
          <visible>F</visible>
          <mandatory>F</mandatory>
          <displayType>NORMAL</displayType>
          <columnBreak>F</columnBreak>
          <sameRowAsPrevious>F</sameRowAsPrevious>
        </field>
        <field>
          <id>[scriptid=custbody_fam_lp_assetdesc]</id>
          <label>Asset Description</label>
          <visible>F</visible>
          <mandatory>F</mandatory>
          <displayType>NORMAL</displayType>
          <columnBreak>F</columnBreak>
          <sameRowAsPrevious>F</sameRowAsPrevious>
        </field>
        <field>
          <id>[scriptid=custbody_fam_lp_startdate]</id>
          <label>Lease Start Date</label>
          <visible>F</visible>
          <mandatory>T</mandatory>
          <displayType>NORMAL</displayType>
          <columnBreak>F</columnBreak>
          <sameRowAsPrevious>F</sameRowAsPrevious>
        </field>
        <field>
          <id>[scriptid=custbody_fam_lp_financelease]</id>
          <label>Finance Lease</label>
          <visible>F</visible>
          <mandatory>F</mandatory>
          <displayType>NORMAL</displayType>
          <columnBreak>F</columnBreak>
          <sameRowAsPrevious>F</sameRowAsPrevious>
          <checkBoxDefault>USE_FIELD_DEFAULT</checkBoxDefault>
        </field>
        <field>
          <id>[scriptid=custbody_fam_lp_assetprop]</id>
          <label>Asset Proposal</label>
          <visible>F</visible>
          <mandatory>F</mandatory>
          <displayType>INLINETEXT</displayType>
          <columnBreak>F</columnBreak>
          <sameRowAsPrevious>F</sameRowAsPrevious>
        </field>
        <field>
          <id>[scriptid=custbody_fam_lp_asset]</id>
          <label>Asset</label>
          <visible>F</visible>
          <mandatory>F</mandatory>
          <displayType>INLINETEXT</displayType>
          <columnBreak>F</columnBreak>
          <sameRowAsPrevious>F</sameRowAsPrevious>
        </field>
        <field>
          <id>[scriptid=custbody_fam_lp_totalleasepayment]</id>
          <label>Total Lease Payment</label>
          <visible>F</visible>
          <mandatory>F</mandatory>
          <displayType>INLINETEXT</displayType>
          <columnBreak>F</columnBreak>
          <sameRowAsPrevious>F</sameRowAsPrevious>
        </field>
        <field>
          <id>[scriptid=custbody_fam_lp_totalnpv]</id>
          <label>Total NPV</label>
          <visible>F</visible>
          <mandatory>F</mandatory>
          <displayType>INLINETEXT</displayType>
          <columnBreak>F</columnBreak>
          <sameRowAsPrevious>F</sameRowAsPrevious>
        </field>
        <field>
          <id>[scriptid=custbody_fam_lp_totalleaseliab]</id>
          <label>Total Lease Liability</label>
          <visible>F</visible>
          <mandatory>F</mandatory>
          <displayType>INLINETEXT</displayType>
          <columnBreak>F</columnBreak>
          <sameRowAsPrevious>F</sameRowAsPrevious>
        </field>
        <field>
          <id>[scriptid=custbody_fam_lp_totalinterest]</id>
          <label>Total Interest</label>
          <visible>F</visible>
          <mandatory>F</mandatory>
          <displayType>INLINETEXT</displayType>
          <columnBreak>F</columnBreak>
          <sameRowAsPrevious>F</sameRowAsPrevious>
        </field>
        <field>
          <id>[scriptid=custbody_fam_lp_totalprincipal]</id>
          <label>Total Principal</label>
          <visible>F</visible>
          <mandatory>F</mandatory>
          <displayType>INLINETEXT</displayType>
          <columnBreak>F</columnBreak>
          <sameRowAsPrevious>F</sameRowAsPrevious>
        </field>
        <field>
          <id>[scriptid=custbody_fam_lp_rentalfreq]</id>
          <label>Rental Frequency</label>
          <visible>F</visible>
          <mandatory>T</mandatory>
          <displayType>NORMAL</displayType>
          <columnBreak>F</columnBreak>
          <sameRowAsPrevious>F</sameRowAsPrevious>
        </field>
        <field>
          <id>[scriptid=custbody_fam_lp_term]</id>
          <label>Lease Term</label>
          <visible>F</visible>
          <mandatory>T</mandatory>
          <displayType>NORMAL</displayType>
          <columnBreak>F</columnBreak>
          <sameRowAsPrevious>F</sameRowAsPrevious>
        </field>
        <field>
          <id>[scriptid=custbody_fam_lp_annualrate]</id>
          <label>Annual Interest Rate</label>
          <visible>F</visible>
          <mandatory>T</mandatory>
          <displayType>NORMAL</displayType>
          <columnBreak>F</columnBreak>
          <sameRowAsPrevious>F</sameRowAsPrevious>
        </field>
        <field>
          <id>[scriptid=custbody_fam_lp_enddate]</id>
          <label>Lease End Date</label>
          <visible>F</visible>
          <mandatory>T</mandatory>
          <displayType>NORMAL</displayType>
          <columnBreak>F</columnBreak>
          <sameRowAsPrevious>F</sameRowAsPrevious>
        </field>
        <field>
          <id>[scriptid=custbody_fam_lp_journal]</id>
          <label>Transaction</label>
          <visible>F</visible>
          <mandatory>F</mandatory>
          <displayType>INLINETEXT</displayType>
          <columnBreak>F</columnBreak>
          <sameRowAsPrevious>F</sameRowAsPrevious>
        </field>
        <field>
          <id>[scriptid=custbody_9997_is_for_ep_eft]</id>
          <label>For Electronic Bank Payment</label>
          <visible>F</visible>
          <mandatory>F</mandatory>
          <displayType>NORMAL</displayType>
          <columnBreak>F</columnBreak>
          <sameRowAsPrevious>F</sameRowAsPrevious>
          <checkBoxDefault>USE_FIELD_DEFAULT</checkBoxDefault>
        </field>
        <field>
          <id>[scriptid=custbody_oro_1230_locale]</id>
          <label>Locale</label>
          <visible>F</visible>
          <mandatory>F</mandatory>
          <displayType>NORMAL</displayType>
          <columnBreak>F</columnBreak>
          <sameRowAsPrevious>F</sameRowAsPrevious>
        </field>
        <field>
          <id>[scriptid=custbody_ste_oss_country]</id>
          <label>OSS Country (2)</label>
          <visible>F</visible>
          <mandatory>F</mandatory>
          <displayType>NORMAL</displayType>
          <columnBreak>F</columnBreak>
          <sameRowAsPrevious>F</sameRowAsPrevious>
        </field>
        <field>
          <id>[scriptid=custbody_ste_oss_scheme]</id>
          <label>OSS Scheme</label>
          <visible>F</visible>
          <mandatory>F</mandatory>
          <displayType>NORMAL</displayType>
          <columnBreak>F</columnBreak>
          <sameRowAsPrevious>F</sameRowAsPrevious>
        </field>
        <field>
          <id>[scriptid=custbody_15699_exclude_from_ep_process]</id>
          <label>Exclude from Electronic Bank Payments Processing</label>
          <visible>F</visible>
          <mandatory>F</mandatory>
          <displayType>NORMAL</displayType>
          <columnBreak>F</columnBreak>
          <sameRowAsPrevious>F</sameRowAsPrevious>
          <checkBoxDefault>USE_FIELD_DEFAULT</checkBoxDefault>
        </field>
      </fields>
    </defaultFieldGroup>
  </mainFields>
  <tabs>
    <tab>
      <id>APPLICATIONS</id>
      <label>Apply</label>
      <visible>T</visible>
      <fieldGroups>
        <defaultFieldGroup/>
      </fieldGroups>
      <subItems/>
    </tab>
    <tab>
      <id>PAYEEADDRESS</id>
      <label>Payee Address</label>
      <visible>T</visible>
      <fieldGroups>
        <defaultFieldGroup>
          <fields position="MIDDLE">
            <field>
              <id>PAYEEADDRESSLIST</id>
              <label>Address To Select</label>
              <visible>T</visible>
              <mandatory>F</mandatory>
              <displayType>NORMAL</displayType>
              <columnBreak>F</columnBreak>
              <sameRowAsPrevious>F</sameRowAsPrevious>
            </field>
            <field>
              <id>ADDRESS</id>
              <label>Pay To</label>
              <visible>T</visible>
              <mandatory>F</mandatory>
              <displayType>NORMAL</displayType>
              <columnBreak>F</columnBreak>
              <sameRowAsPrevious>F</sameRowAsPrevious>
            </field>
          </fields>
        </defaultFieldGroup>
      </fieldGroups>
      <subItems/>
    </tab>
    <tab>
      <id>TRANSACTIONRELATIONSHIPS</id>
      <label>Relationships</label>
      <visible>T</visible>
      <fieldGroups>
        <defaultFieldGroup/>
      </fieldGroups>
      <subItems>
        <subList>
          <id>CRMCONTACTS</id>
          <label>Contacts</label>
          <visible>T</visible>
          <neverEmpty>F</neverEmpty>
        </subList>
      </subItems>
    </tab>
    <tab>
      <id>TRANSACTIONCOMMUNICATION</id>
      <label>Communication</label>
      <visible>T</visible>
      <fieldGroups>
        <defaultFieldGroup/>
      </fieldGroups>
      <subItems>
        <subList>
          <id>MESSAGES</id>
          <label>Messages</label>
          <visible>T</visible>
          <neverEmpty>F</neverEmpty>
        </subList>
        <subList>
          <id>ACTIVITIES</id>
          <label>Activities</label>
          <visible>T</visible>
          <neverEmpty>F</neverEmpty>
        </subList>
        <subList>
          <id>EVENTS</id>
          <label>Events</label>
          <visible>F</visible>
          <neverEmpty>F</neverEmpty>
        </subList>
        <subList>
          <id>TASKS</id>
          <label>Tasks</label>
          <visible>F</visible>
          <neverEmpty>F</neverEmpty>
        </subList>
        <subList>
          <id>CALLS</id>
          <label>Phone Calls</label>
          <visible>F</visible>
          <neverEmpty>F</neverEmpty>
        </subList>
        <subList>
          <id>MEDIAITEM</id>
          <label>Files</label>
          <visible>T</visible>
          <neverEmpty>F</neverEmpty>
        </subList>
        <subList>
          <id>USERNOTES</id>
          <label>User Notes</label>
          <visible>T</visible>
          <neverEmpty>F</neverEmpty>
        </subList>
      </subItems>
    </tab>
    <tab>
      <id>TRANSACTIONSYSTEMINFORMATION</id>
      <label>System Information</label>
      <visible>T</visible>
      <fieldGroups>
        <defaultFieldGroup>
          <fields position="MIDDLE">
            <field>
              <id>CUSTOMFORM</id>
              <label>Custom Form</label>
              <visible>T</visible>
              <mandatory>T</mandatory>
              <displayType>NORMAL</displayType>
              <columnBreak>F</columnBreak>
              <sameRowAsPrevious>F</sameRowAsPrevious>
            </field>
          </fields>
        </defaultFieldGroup>
      </fieldGroups>
      <subItems>
        <subList>
          <id>SYSTEMNOTES</id>
          <label>System Notes</label>
          <visible>T</visible>
          <neverEmpty>F</neverEmpty>
        </subList>
        <subList>
          <id>ACTIVEWORKFLOWS</id>
          <label>Active Workflows</label>
          <visible>T</visible>
          <neverEmpty>F</neverEmpty>
        </subList>
        <subList>
          <id>WORKFLOWHISTORY</id>
          <label>Workflow History</label>
          <visible>T</visible>
          <neverEmpty>F</neverEmpty>
        </subList>
      </subItems>
    </tab>
    <tab>
      <id>CUSTOM</id>
      <label>Custom</label>
      <visible>T</visible>
      <fieldGroups>
        <defaultFieldGroup>
          <fields position="MIDDLE">
            <field>
              <id>[scriptid=custbody_oro_3010_pay_method]</id>
              <label>EFT Payment Method</label>
              <visible>F</visible>
              <mandatory>F</mandatory>
              <displayType>NORMAL</displayType>
              <columnBreak>F</columnBreak>
              <sameRowAsPrevious>F</sameRowAsPrevious>
            </field>
            <field>
              <id>[scriptid=custbody_fam_specdeprjrn_rate]</id>
              <label>Rate</label>
              <visible>F</visible>
              <mandatory>F</mandatory>
              <displayType>NORMAL</displayType>
              <columnBreak>F</columnBreak>
              <sameRowAsPrevious>F</sameRowAsPrevious>
            </field>
            <field>
              <id>[scriptid=custbody_fam_specdeprjrn_limit]</id>
              <label>Limit</label>
              <visible>F</visible>
              <mandatory>F</mandatory>
              <displayType>NORMAL</displayType>
              <columnBreak>F</columnBreak>
              <sameRowAsPrevious>F</sameRowAsPrevious>
            </field>
            <field>
              <id>[scriptid=custbody_fam_specdeprjrn_term1]</id>
              <label>Applied Term 1</label>
              <visible>F</visible>
              <mandatory>F</mandatory>
              <displayType>NORMAL</displayType>
              <columnBreak>F</columnBreak>
              <sameRowAsPrevious>F</sameRowAsPrevious>
            </field>
            <field>
              <id>[scriptid=custbody_fam_specdeprjrn_term2]</id>
              <label>Applied Term 2</label>
              <visible>F</visible>
              <mandatory>F</mandatory>
              <displayType>NORMAL</displayType>
              <columnBreak>F</columnBreak>
              <sameRowAsPrevious>F</sameRowAsPrevious>
            </field>
            <field>
              <id>[scriptid=custbody_fam_specdeprjrn_shortage]</id>
              <label>Shortage</label>
              <visible>F</visible>
              <mandatory>F</mandatory>
              <displayType>NORMAL</displayType>
              <columnBreak>F</columnBreak>
              <sameRowAsPrevious>F</sameRowAsPrevious>
            </field>
            <field>
              <id>[scriptid=custbody_oro_21_integrid]</id>
              <label>Integration Id</label>
              <visible>F</visible>
              <mandatory>F</mandatory>
              <displayType>INLINETEXT</displayType>
              <columnBreak>F</columnBreak>
              <sameRowAsPrevious>F</sameRowAsPrevious>
            </field>
            <field>
              <id>[scriptid=custbody_oro_21_integrtype]</id>
              <label>Integration Type</label>
              <visible>F</visible>
              <mandatory>F</mandatory>
              <displayType>INLINETEXT</displayType>
              <columnBreak>F</columnBreak>
              <sameRowAsPrevious>F</sameRowAsPrevious>
            </field>
            <field>
              <id>[scriptid=custbody_oro_1230_sourced_print_data]</id>
              <label>Additional Data for PDF Print</label>
              <visible>F</visible>
              <mandatory>F</mandatory>
              <displayType>NORMAL</displayType>
              <columnBreak>F</columnBreak>
              <sameRowAsPrevious>F</sameRowAsPrevious>
            </field>
            <field>
              <id>[type=transactionbodycustomfield, scriptid=cseg_oro_brand]</id>
              <label>Brand (8)</label>
              <visible>F</visible>
              <mandatory>F</mandatory>
              <displayType>NORMAL</displayType>
              <columnBreak>F</columnBreak>
              <sameRowAsPrevious>F</sameRowAsPrevious>
            </field>
            <field>
              <id>[type=transactionbodycustomfield, scriptid=cseg_oro_tour]</id>
              <label>Tour (6)</label>
              <visible>F</visible>
              <mandatory>F</mandatory>
              <displayType>NORMAL</displayType>
              <columnBreak>F</columnBreak>
              <sameRowAsPrevious>F</sameRowAsPrevious>
            </field>
            <field>
              <id>[type=transactionbodycustomfield, scriptid=cseg_oro_vessel]</id>
              <label>Vessel (8)</label>
              <visible>F</visible>
              <mandatory>F</mandatory>
              <displayType>NORMAL</displayType>
              <columnBreak>F</columnBreak>
              <sameRowAsPrevious>F</sameRowAsPrevious>
            </field>
            <field>
              <id>[scriptid=custbody_oro_1990_ste_fxrate_taxdate]</id>
              <label>Tax Nexus Exchange Rate (Tax Point Date)</label>
              <visible>F</visible>
              <mandatory>F</mandatory>
              <displayType>NORMAL</displayType>
              <columnBreak>F</columnBreak>
              <sameRowAsPrevious>F</sameRowAsPrevious>
            </field>
            <field>
              <id>[scriptid=custbody_oro_1990_ste_fxrate_trandate]</id>
              <label>Tax Nexus Exchange Rate (Transaction Date)</label>
              <visible>F</visible>
              <mandatory>F</mandatory>
              <displayType>NORMAL</displayType>
              <columnBreak>F</columnBreak>
              <sameRowAsPrevious>F</sameRowAsPrevious>
            </field>
            <field>
              <id>[scriptid=custbody_oro_def_vat_reg_num]</id>
              <label>Default VAT Reg Num</label>
              <visible>F</visible>
              <mandatory>F</mandatory>
              <displayType>NORMAL</displayType>
              <columnBreak>F</columnBreak>
              <sameRowAsPrevious>F</sameRowAsPrevious>
            </field>
          </fields>
        </defaultFieldGroup>
      </fieldGroups>
      <subItems/>
    </tab>
    <tab>
      <id>GLIMPACTTAB</id>
      <label>GL Impact</label>
      <visible>T</visible>
      <fieldGroups>
        <defaultFieldGroup/>
      </fieldGroups>
      <subItems>
        <subList>
          <id>GLIMPACTCHANGES</id>
          <label>GL Impact Changes</label>
          <visible>T</visible>
          <neverEmpty>F</neverEmpty>
        </subList>
      </subItems>
    </tab>
    <tab>
      <id>TRANSACTIONRELATEDRECORDS</id>
      <label>Related Records</label>
      <visible>T</visible>
      <fieldGroups>
        <defaultFieldGroup/>
      </fieldGroups>
      <subItems>
        <subList>
          <id>ITPRLRCDS</id>
          <label>Related Records</label>
          <visible>T</visible>
          <neverEmpty>F</neverEmpty>
        </subList>
      </subItems>
    </tab>
    <tab>
      <id>[scriptid=custtab_str_transaction_tab]</id>
      <label>Tax Reporting</label>
      <visible>T</visible>
      <fieldGroups>
        <defaultFieldGroup>
          <fields position="MIDDLE">
            <field>
              <id>[scriptid=custbody_str_incoterm]</id>
              <label>Incoterm</label>
              <visible>F</visible>
              <mandatory>F</mandatory>
              <displayType>NORMAL</displayType>
              <columnBreak>F</columnBreak>
              <sameRowAsPrevious>F</sameRowAsPrevious>
            </field>
            <field>
              <id>[scriptid=custbody_str_transport_mode]</id>
              <label>Mode of transport</label>
              <visible>F</visible>
              <mandatory>F</mandatory>
              <displayType>NORMAL</displayType>
              <columnBreak>F</columnBreak>
              <sameRowAsPrevious>F</sameRowAsPrevious>
            </field>
            <field>
              <id>[scriptid=custbody_str_notc]</id>
              <label>Nature of Transaction</label>
              <visible>F</visible>
              <mandatory>F</mandatory>
              <displayType>NORMAL</displayType>
              <columnBreak>F</columnBreak>
              <sameRowAsPrevious>F</sameRowAsPrevious>
            </field>
            <field>
              <id>[scriptid=custbody_str_region_of_destination]</id>
              <label>Region of Destination</label>
              <visible>F</visible>
              <mandatory>F</mandatory>
              <displayType>NORMAL</displayType>
              <columnBreak>F</columnBreak>
              <sameRowAsPrevious>F</sameRowAsPrevious>
            </field>
            <field>
              <id>[scriptid=custbody_str_region_of_origin]</id>
              <label>Region of Origin</label>
              <visible>F</visible>
              <mandatory>F</mandatory>
              <displayType>NORMAL</displayType>
              <columnBreak>F</columnBreak>
              <sameRowAsPrevious>F</sameRowAsPrevious>
            </field>
            <field>
              <id>[scriptid=custbody_str_statistical_proc]</id>
              <label>Statistical Procedure</label>
              <visible>F</visible>
              <mandatory>F</mandatory>
              <displayType>NORMAL</displayType>
              <columnBreak>F</columnBreak>
              <sameRowAsPrevious>F</sameRowAsPrevious>
            </field>
            <field>
              <id>[scriptid=custbody_str_fr_department]</id>
              <label>French Department</label>
              <visible>F</visible>
              <mandatory>F</mandatory>
              <displayType>NORMAL</displayType>
              <columnBreak>F</columnBreak>
              <sameRowAsPrevious>F</sameRowAsPrevious>
            </field>
            <field>
              <id>[scriptid=custbody_str_regime_code]</id>
              <label>Regime Code</label>
              <visible>F</visible>
              <mandatory>F</mandatory>
              <displayType>NORMAL</displayType>
              <columnBreak>F</columnBreak>
              <sameRowAsPrevious>F</sameRowAsPrevious>
            </field>
            <field>
              <id>[scriptid=custbody_establishment_code]</id>
              <label>Establishment Code</label>
              <visible>F</visible>
              <mandatory>F</mandatory>
              <displayType>NORMAL</displayType>
              <columnBreak>F</columnBreak>
              <sameRowAsPrevious>F</sameRowAsPrevious>
            </field>
            <field>
              <id>[scriptid=custbody_emea_country_of_origin]</id>
              <label>Country of Origin (2)</label>
              <visible>F</visible>
              <mandatory>F</mandatory>
              <displayType>NORMAL</displayType>
              <columnBreak>F</columnBreak>
              <sameRowAsPrevious>F</sameRowAsPrevious>
            </field>
          </fields>
        </defaultFieldGroup>
      </fieldGroups>
      <subItems/>
    </tab>
    <tab>
      <id>[scriptid=custtab_31_5435884_159]</id>
      <label>Posting Reference</label>
      <visible>T</visible>
      <fieldGroups>
        <defaultFieldGroup>
          <fields position="MIDDLE">
            <field>
              <id>[scriptid=custbody_fam_lp_rightofuse]</id>
              <label>Right-of-Use Asset</label>
              <visible>F</visible>
              <mandatory>T</mandatory>
              <displayType>NORMAL</displayType>
              <columnBreak>F</columnBreak>
              <sameRowAsPrevious>F</sameRowAsPrevious>
            </field>
            <field>
              <id>[scriptid=custbody_fam_lp_leaseliability]</id>
              <label>Lease Liability</label>
              <visible>F</visible>
              <mandatory>T</mandatory>
              <displayType>NORMAL</displayType>
              <columnBreak>F</columnBreak>
              <sameRowAsPrevious>F</sameRowAsPrevious>
            </field>
            <field>
              <id>[scriptid=custbody_fam_lp_intexpense]</id>
              <label>Interest Expense</label>
              <visible>F</visible>
              <mandatory>T</mandatory>
              <displayType>NORMAL</displayType>
              <columnBreak>F</columnBreak>
              <sameRowAsPrevious>F</sameRowAsPrevious>
            </field>
            <field>
              <id>[scriptid=custbody_fam_lp_gainonmod]</id>
              <label>Gain (Loss) on Modification</label>
              <visible>F</visible>
              <mandatory>F</mandatory>
              <displayType>NORMAL</displayType>
              <columnBreak>F</columnBreak>
              <sameRowAsPrevious>F</sameRowAsPrevious>
            </field>
          </fields>
        </defaultFieldGroup>
      </fieldGroups>
      <subItems/>
    </tab>
    <tab>
      <id>[scriptid=custtab_9_4533432_230]</id>
      <label>EFT</label>
      <visible>T</visible>
      <fieldGroups>
        <defaultFieldGroup>
          <fields position="MIDDLE">
            <field>
              <id>[scriptid=custbody_11187_pref_entity_bank]</id>
              <label>Preferred Entity Bank</label>
              <visible>T</visible>
              <mandatory>F</mandatory>
              <displayType>NORMAL</displayType>
              <columnBreak>F</columnBreak>
              <sameRowAsPrevious>F</sameRowAsPrevious>
            </field>
            <field>
              <id>[scriptid=custbody_11724_bank_fee]</id>
              <label>Bank Fee</label>
              <visible>T</visible>
              <mandatory>F</mandatory>
              <displayType>NORMAL</displayType>
              <columnBreak>F</columnBreak>
              <sameRowAsPrevious>F</sameRowAsPrevious>
            </field>
            <field>
              <id>[scriptid=custbody_9997_pfa_record]</id>
              <label>PFA-record</label>
              <visible>T</visible>
              <mandatory>F</mandatory>
              <displayType>INLINETEXT</displayType>
              <columnBreak>F</columnBreak>
              <sameRowAsPrevious>F</sameRowAsPrevious>
            </field>
            <field>
              <id>[scriptid=custbody_15529_vendor_entity_bank]</id>
              <label>Entity Bank (Vendor)</label>
              <visible>T</visible>
              <mandatory>F</mandatory>
              <displayType>NORMAL</displayType>
              <columnBreak>F</columnBreak>
              <sameRowAsPrevious>F</sameRowAsPrevious>
            </field>
            <field>
              <id>[scriptid=custbody_15529_emp_entity_bank]</id>
              <label>Entity Bank (Employee)</label>
              <visible>T</visible>
              <mandatory>F</mandatory>
              <displayType>NORMAL</displayType>
              <columnBreak>F</columnBreak>
              <sameRowAsPrevious>F</sameRowAsPrevious>
            </field>
            <field>
              <id>[scriptid=custbody_10184_customer_entity_bank]</id>
              <label>Entity Bank (Customer)</label>
              <visible>F</visible>
              <mandatory>F</mandatory>
              <displayType>NORMAL</displayType>
              <columnBreak>F</columnBreak>
              <sameRowAsPrevious>F</sameRowAsPrevious>
            </field>
          </fields>
        </defaultFieldGroup>
      </fieldGroups>
      <subItems/>
    </tab>
    <tab>
      <id>[scriptid=custtab_363_6796187_558]</id>
      <label>Order Details</label>
      <visible>T</visible>
      <fieldGroups>
        <defaultFieldGroup/>
      </fieldGroups>
      <subItems/>
    </tab>
    <tab>
      <id>[scriptid=custtab_364_6796187_393]</id>
      <label>Sales Details</label>
      <visible>T</visible>
      <fieldGroups>
        <defaultFieldGroup/>
      </fieldGroups>
      <subItems/>
    </tab>
    <tab>
      <id>[scriptid=custtab_479_6796187_575]</id>
      <label>Invoice Bank Details</label>
      <visible>T</visible>
      <fieldGroups>
        <defaultFieldGroup>
          <fields position="MIDDLE">
            <field>
              <id>[scriptid=custbody_sce_bd_iban]</id>
              <label>BD IBAN</label>
              <visible>F</visible>
              <mandatory>F</mandatory>
              <displayType>NORMAL</displayType>
              <columnBreak>F</columnBreak>
              <sameRowAsPrevious>F</sameRowAsPrevious>
            </field>
            <field>
              <id>[scriptid=custbody_sce_bd_overridebd]</id>
              <label>Override Bank Details</label>
              <visible>F</visible>
              <mandatory>F</mandatory>
              <displayType>NORMAL</displayType>
              <columnBreak>F</columnBreak>
              <sameRowAsPrevious>F</sameRowAsPrevious>
              <checkBoxDefault>USE_FIELD_DEFAULT</checkBoxDefault>
            </field>
            <field>
              <id>[scriptid=custbody_sce_bd_bic]</id>
              <label>BD BIC</label>
              <visible>F</visible>
              <mandatory>F</mandatory>
              <displayType>NORMAL</displayType>
              <columnBreak>F</columnBreak>
              <sameRowAsPrevious>F</sameRowAsPrevious>
            </field>
            <field>
              <id>[scriptid=custbody_sce_bd_sortcode]</id>
              <label>BD Sort Code</label>
              <visible>F</visible>
              <mandatory>F</mandatory>
              <displayType>NORMAL</displayType>
              <columnBreak>F</columnBreak>
              <sameRowAsPrevious>F</sameRowAsPrevious>
            </field>
            <field>
              <id>[scriptid=custbody_sce_bd_bsb]</id>
              <label>BD BSB</label>
              <visible>F</visible>
              <mandatory>F</mandatory>
              <displayType>NORMAL</displayType>
              <columnBreak>F</columnBreak>
              <sameRowAsPrevious>F</sameRowAsPrevious>
            </field>
            <field>
              <id>[scriptid=custbody_sce_bd_bankaddr]</id>
              <label>BD Bank Address</label>
              <visible>F</visible>
              <mandatory>F</mandatory>
              <displayType>NORMAL</displayType>
              <columnBreak>F</columnBreak>
              <sameRowAsPrevious>F</sameRowAsPrevious>
            </field>
            <field>
              <id>[scriptid=custbody_sce_bd_bankname]</id>
              <label>BD Bank Name</label>
              <visible>F</visible>
              <mandatory>F</mandatory>
              <displayType>NORMAL</displayType>
              <columnBreak>F</columnBreak>
              <sameRowAsPrevious>F</sameRowAsPrevious>
            </field>
          </fields>
        </defaultFieldGroup>
      </fieldGroups>
      <subItems/>
    </tab>
  </tabs>
  <actionbar>
    <buttons>
      <button>
        <id>VOID</id>
        <label>Void</label>
        <visible>T</visible>
      </button>
    </buttons>
    <menu>
      <menuitem>
        <id>DELETE</id>
        <label>Delete</label>
        <visible>T</visible>
      </menuitem>
      <menuitem>
        <id>EMAIL</id>
        <label>Email</label>
        <visible>T</visible>
      </menuitem>
      <menuitem>
        <id>FAX</id>
        <label>Fax</label>
        <visible>T</visible>
      </menuitem>
      <menuitem>
        <id>GLIMPACT</id>
        <label>GL Impact</label>
        <visible>T</visible>
      </menuitem>
      <menuitem>
        <id>GOTOREGISTER</id>
        <label>Go To Register</label>
        <visible>T</visible>
      </menuitem>
      <menuitem>
        <id>NEW</id>
        <label>New</label>
        <visible>T</visible>
      </menuitem>
      <menuitem>
        <id>PRINT</id>
        <label>Print</label>
        <visible>T</visible>
      </menuitem>
      <menuitem>
        <id>PRINTGLIMPACT</id>
        <label>Print GL Impact</label>
        <visible>T</visible>
      </menuitem>
      <menuitem>
        <id>SAVEEMAIL</id>
        <label>Save &amp; Email</label>
        <visible>T</visible>
      </menuitem>
      <menuitem>
        <id>SUBMITNEW</id>
        <label>Save &amp; New</label>
        <visible>T</visible>
      </menuitem>
      <menuitem>
        <id>SAVEPRINT</id>
        <label>Save &amp; Print</label>
        <visible>T</visible>
      </menuitem>
      <menuitem>
        <id>ACTIVITYHISTORY</id>
        <label>Show Activity</label>
        <visible>T</visible>
      </menuitem>
    </menu>
  </actionbar>
  <disclaimer/>
  <address/>
  <emailMessageTemplate>USE_DEFAULT</emailMessageTemplate>
  <printingType>
    <advanced>
      <printTemplate>STDTMPLAUVENDPYMT</printTemplate>
      <emailTemplate>STDTMPLAUVENDPYMT</emailTemplate>
    </advanced>
  </printingType>
  <roles>
    <role>
      <id>[scriptid=customrole1242]</id>
      <preferred>F</preferred>
    </role>
    <role>
      <id>[scriptid=customrole1013]</id>
      <preferred>F</preferred>
    </role>
    <role>
      <id>[scriptid=customrole1014]</id>
      <preferred>F</preferred>
    </role>
    <role>
      <id>[scriptid=customrole1029]</id>
      <preferred>F</preferred>
    </role>
    <role>
      <id>AP_CLERK</id>
      <preferred>F</preferred>
    </role>
    <role>
      <id>ACCOUNTANT</id>
      <preferred>F</preferred>
    </role>
    <role>
      <id>ADMINISTRATOR</id>
      <preferred>F</preferred>
    </role>
    <role>
      <id>BOOKKEEPER</id>
      <preferred>F</preferred>
    </role>
    <role>
      <id>CEO</id>
      <preferred>F</preferred>
    </role>
    <role>
      <id>CEO_HANDS_OFF</id>
      <preferred>F</preferred>
    </role>
    <role>
      <id>CUSTOMROLE41</id>
      <preferred>F</preferred>
    </role>
    <role>
      <id>[scriptid=customrole1002]</id>
      <preferred>F</preferred>
    </role>
    <role>
      <id>[scriptid=customrole_ep_approver]</id>
      <preferred>F</preferred>
    </role>
    <role>
      <id>[scriptid=customrole_ep_configurator]</id>
      <preferred>F</preferred>
    </role>
    <role>
      <id>[scriptid=customrole_ep_processor]</id>
      <preferred>F</preferred>
    </role>
    <role>
      <id>[scriptid=customrolecustomrole1013]</id>
      <preferred>F</preferred>
    </role>
    <role>
      <id>FULL_ACCESS</id>
      <preferred>F</preferred>
    </role>
    <role>
      <id>[scriptid=customrole1246]</id>
      <preferred>F</preferred>
    </role>
    <role>
      <id>[scriptid=customrole1140]</id>
      <preferred>F</preferred>
    </role>
    <role>
      <id>[scriptid=customrole_nspbcs_implementer]</id>
      <preferred>F</preferred>
    </role>
    <role>
      <id>[scriptid=customrole_nspbcs_pbcs_integration]</id>
      <preferred>F</preferred>
    </role>
    <role>
      <id>[scriptid=customrole1245]</id>
      <preferred>F</preferred>
    </role>
    <role>
      <id>[scriptid=customrole1028]</id>
      <preferred>F</preferred>
    </role>
    <role>
      <id>[scriptid=customrole1249]</id>
      <preferred>F</preferred>
    </role>
    <role>
      <id>[scriptid=customrole1243]</id>
      <preferred>F</preferred>
    </role>
    <role>
      <id>[scriptid=customrole1244]</id>
      <preferred>F</preferred>
    </role>
    <role>
      <id>[scriptid=customrole1138]</id>
      <preferred>F</preferred>
    </role>
    <role>
      <id>[scriptid=customrole_oro_accounting]</id>
      <preferred>F</preferred>
    </role>
    <role>
      <id>[scriptid=customrole_oro_21k_integration]</id>
      <preferred>F</preferred>
    </role>
  </roles>
</transactionForm>
